{
  "total": 1956,
  "alive": 1235,
  "dead": 721,
  "byProtocol": {
    "vless": {
      "total": 1070,
      "alive": 794
    },
    "ss": {
      "total": 534,
      "alive": 142
    },
    "trojan": {
      "total": 304,
      "alive": 286
    },
    "vmess": {
      "total": 48,
      "alive": 13
    }
  },
  "byCountry": {
    "CA": {
      "total": 439,
      "alive": 434
    },
    "US": {
      "total": 173,
      "alive": 149
    },
    "RU": {
      "total": 150,
      "alive": 91
    },
    "DE": {
      "total": 125,
      "alive": 82
    },
    "PL": {
      "total": 111,
      "alive": 10
    },
    "JP": {
      "total": 81,
      "alive": 78
    },
    "UN": {
      "total": 81,
      "alive": 0
    },
    "VN": {
      "total": 80,
      "alive": 0
    },
    "GB": {
      "total": 79,
      "alive": 71
    },
    "NL": {
      "total": 69,
      "alive": 43
    },
    "FR": {
      "total": 55,
      "alive": 36
    },
    "SG": {
      "total": 48,
      "alive": 35
    },
    "SC": {
      "total": 45,
      "alive": 24
    },
    "CY": {
      "total": 31,
      "alive": 23
    },
    "KR": {
      "total": 31,
      "alive": 31
    },
    "FI": {
      "total": 28,
      "alive": 14
    },
    "IR": {
      "total": 21,
      "alive": 5
    },
    "SE": {
      "total": 18,
      "alive": 8
    },
    "HK": {
      "total": 17,
      "alive": 8
    },
    "MD": {
      "total": 15,
      "alive": 1
    },
    "AE": {
      "total": 13,
      "alive": 10
    },
    "AU": {
      "total": 12,
      "alive": 6
    },
    "BR": {
      "total": 12,
      "alive": 0
    },
    "IT": {
      "total": 11,
      "alive": 6
    },
    "KZ": {
      "total": 11,
      "alive": 3
    },
    "SA": {
      "total": 11,
      "alive": 0
    },
    "CH": {
      "total": 10,
      "alive": 5
    },
    "IN": {
      "total": 10,
      "alive": 5
    },
    "GR": {
      "total": 10,
      "alive": 0
    },
    "IL": {
      "total": 10,
      "alive": 0
    },
    "IE": {
      "total": 9,
      "alive": 9
    },
    "LT": {
      "total": 9,
      "alive": 4
    },
    "MY": {
      "total": 9,
      "alive": 2
    },
    "TR": {
      "total": 8,
      "alive": 2
    },
    "ES": {
      "total": 7,
      "alive": 4
    },
    "EE": {
      "total": 7,
      "alive": 3
    },
    "EG": {
      "total": 7,
      "alive": 1
    },
    "JO": {
      "total": 7,
      "alive": 0
    },
    "KW": {
      "total": 7,
      "alive": 0
    },
    "UA": {
      "total": 7,
      "alive": 0
    },
    "HU": {
      "total": 6,
      "alive": 0
    },
    "RO": {
      "total": 5,
      "alive": 3
    },
    "PK": {
      "total": 5,
      "alive": 0
    },
    "ZA": {
      "total": 4,
      "alive": 4
    },
    "BG": {
      "total": 3,
      "alive": 1
    },
    "TW": {
      "total": 3,
      "alive": 3
    },
    "AT": {
      "total": 3,
      "alive": 3
    },
    "BE": {
      "total": 3,
      "alive": 3
    },
    "LV": {
      "total": 3,
      "alive": 2
    },
    "NO": {
      "total": 3,
      "alive": 2
    },
    "KH": {
      "total": 3,
      "alive": 0
    },
    "AR": {
      "total": 3,
      "alive": 0
    },
    "MX": {
      "total": 3,
      "alive": 0
    },
    "SK": {
      "total": 2,
      "alive": 1
    },
    "CZ": {
      "total": 2,
      "alive": 2
    },
    "SI": {
      "total": 2,
      "alive": 0
    },
    "MT": {
      "total": 2,
      "alive": 1
    },
    "IS": {
      "total": 2,
      "alive": 0
    },
    "MK": {
      "total": 2,
      "alive": 0
    },
    "AL": {
      "total": 2,
      "alive": 2
    },
    "AM": {
      "total": 2,
      "alive": 0
    },
    "NZ": {
      "total": 1,
      "alive": 1
    },
    "MH": {
      "total": 1,
      "alive": 1
    },
    "GE": {
      "total": 1,
      "alive": 1
    },
    "PH": {
      "total": 1,
      "alive": 1
    },
    "PR": {
      "total": 1,
      "alive": 0
    },
    "AZ": {
      "total": 1,
      "alive": 0
    },
    "PT": {
      "total": 1,
      "alive": 0
    },
    "CO": {
      "total": 1,
      "alive": 0
    },
    "BY": {
      "total": 1,
      "alive": 1
    }
  },
  "sources": {
    "https://raw.githubusercontent.com/MrAbolfazlNorouzi/iran-configs/refs/heads/main/configs/working-configs.txt": 5,
    "https://raw.githubusercontent.com/arshiacomplus/v2rayExtractor/refs/heads/main/mix/sub.html": 706,
    "https://raw.githubusercontent.com/4n0nymou3/multi-proxy-config-fetcher/refs/heads/main/configs/proxy_configs.txt": 1096,
    "https://raw.githubusercontent.com/parvinxs/Submahsanetxsparvin/refs/heads/main/Sub.mahsa.xsparvin": 1169,
    "https://raw.githubusercontent.com/mahdibland/V2RayAggregator/master/Eternity.txt": 200,
    "https://raw.githubusercontent.com/Pawdroid/Free-servers/main/sub": 16,
    "t.me/s/v2ray_configs_pool": 5,
    "t.me/s/outline_vpn": 87,
    "t.me/s/V2ray_Alpha": 53,
    "t.me/s/v2rayngvpn": 0,
    "t.me/s/on_proxy1": 42
  },
  "note": "alive = TCP port reachable from GitHub Actions runner (not guaranteed to work inside Iran)",
  "generatedAt": "2026-07-17T14:29:49.027Z"
}